routermonitor/__init__.py
routermonitor/routermonitor.py
routermonitor/deployment_files/creds_SMTP
routermonitor/deployment_files/creds_routermonitor
routermonitor/deployment_files/routermonitor.cfg
routermonitor/deployment_files/routermonitor.service
routermonitor-3.1.dist-info/LICENSE.txt
routermonitor-3.1.dist-info/METADATA
routermonitor-3.1.dist-info/WHEEL
routermonitor-3.1.dist-info/entry_points.txt
routermonitor-3.1.dist-info/top_level.txt
routermonitor-3.1.dist-info/RECORD
