Metadata-Version: 2.1
Name: routermonitor
Version: 3.1
Summary: Watch for new DHCP clients on your LAN
Author-email: Chris Nelson <github@cjnaz.com>
License: MIT License
Project-URL: repository, https://github.com/cjnaz/routermonitor
Classifier: Topic :: System :: Networking :: Monitoring
Requires-Python: >=3.6
License-File: LICENSE.txt
Requires-Dist: cjnfuncs >=2.0.2
Requires-Dist: requests
Requires-Dist: lxml
Requires-Dist: importlib-metadata ; python_version < "3.8"
